LICENSE.txt
MANIFEST.in
README.md
README.txt
setup.cfg
setup.py
prueba_ifsUW/__init__.py
prueba_ifsUW/prueba_ifsUW.py
prueba_ifsUW.egg-info/PKG-INFO
prueba_ifsUW.egg-info/SOURCES.txt
prueba_ifsUW.egg-info/dependency_links.txt
prueba_ifsUW.egg-info/requires.txt
prueba_ifsUW.egg-info/top_level.txt
prueba_ifsUW/Filters/B-Bessell (1990).txt
prueba_ifsUW/Filters/B-Johnson (1965).txt
prueba_ifsUW/Filters/B-KPN0-Harris.txt
prueba_ifsUW/Filters/HALPHA-CTI0 6586-20A.txt
prueba_ifsUW/Filters/Halpha-KPN0 6547-80A.txt
prueba_ifsUW/Filters/R-Bessell.txt
prueba_ifsUW/Filters/R-KPN0-Harris.txt
prueba_ifsUW/Filters/V-Bessell.txt
prueba_ifsUW/Filters/V-Johnson.txt
prueba_ifsUW/Filters/V-KPN0-Harris.txt
prueba_ifsUW/Filters/g-SDSS-III.txt
prueba_ifsUW/Filters/i-SDSS-III.txt
prueba_ifsUW/Filters/r-SDSS-III.txt
prueba_ifsUW/Filters/u-SDSS-III.txt
prueba_ifsUW/Img/logoIFSexplorer.ico
prueba_ifsUW/Img/logoIFSexplorer.png
prueba_ifsUW/Img/logotipo.png