Metadata-Version: 2.1
Name: prueba-ifsUW
Version: 7
Summary: paquete de prueba prueba_ifsUW
Home-page: https://github.com/NildaX/python-prueba_ifsUW
Author: Nilda G.Xolo  Tlapanco
Author-email: nilda_gaby_9745@live.com.mx
License: MIT
Keywords: testing,IFS,example
Platform: UNKNOWN
Classifier: Programming Language :: Python :: 3.4
